{
    "RPT": {
        "ScanTime": "0.02 sec.",
        "ScanFile": "20201125_e58298e5b082e99680e5ba97e5b08f_5a42c6eefb09170d6537_20201125041933_scan.json",
        "Warnings": 0,
        "Success": 6
    },
    "SRV": {
        "PHP": {
            "websrv": true,
            "openbase": true,
            "maxtime": true,
            "mysqli": true,
            "version": true,
            "ALL": "Good"
        },
        "WP": {
            "version": true,
            "core": true,
            "ismu": false,
            "ALL": "Good"
        }
    },
    "ARC": {
        "Size": "0B",
        "DirCount": "0",
        "FileCount": "0",
        "FullCount": "0",
        "WarnFileCount": 0,
        "WarnDirCount": 0,
        "UnreadableDirCount": 0,
        "UnreadableFileCount": 0,
        "FilterDirsAll": [
            "\/home\/komiyakasa\/komiyakasa.jp\/public_html\/.opcache",
            "\/home\/komiyakasa\/komiyakasa.jp\/public_html\/wp-content\/ai1wm-backups",
            "\/home\/komiyakasa\/komiyakasa.jp\/public_html\/wp-content\/backups-dup-lite",
            "\/home\/komiyakasa\/komiyakasa.jp\/public_html\/wp-content\/backups-dup-pro",
            "\/home\/komiyakasa\/komiyakasa.jp\/public_html\/wp-content\/backupwordpress",
            "\/home\/komiyakasa\/komiyakasa.jp\/public_html\/wp-content\/bps-backup",
            "\/home\/komiyakasa\/komiyakasa.jp\/public_html\/wp-content\/cache",
            "\/home\/komiyakasa\/komiyakasa.jp\/public_html\/wp-content\/content\/cache",
            "\/home\/komiyakasa\/komiyakasa.jp\/public_html\/wp-content\/contents\/cache",
            "\/home\/komiyakasa\/komiyakasa.jp\/public_html\/wp-content\/infinitewp\/backups",
            "\/home\/komiyakasa\/komiyakasa.jp\/public_html\/wp-content\/managewp\/backups",
            "\/home\/komiyakasa\/komiyakasa.jp\/public_html\/wp-content\/old-cache",
            "\/home\/komiyakasa\/komiyakasa.jp\/public_html\/wp-content\/plugins\/all-in-one-wp-migration\/storage",
            "\/home\/komiyakasa\/komiyakasa.jp\/public_html\/wp-content\/updraft",
            "\/home\/komiyakasa\/komiyakasa.jp\/public_html\/wp-content\/uploads\/aiowps_backups",
            "\/home\/komiyakasa\/komiyakasa.jp\/public_html\/wp-content\/uploads\/backupbuddy_backups",
            "\/home\/komiyakasa\/komiyakasa.jp\/public_html\/wp-content\/uploads\/backupbuddy_temp",
            "\/home\/komiyakasa\/komiyakasa.jp\/public_html\/wp-content\/uploads\/ithemes-security\/backups",
            "\/home\/komiyakasa\/komiyakasa.jp\/public_html\/wp-content\/uploads\/mainwp\/backup",
            "\/home\/komiyakasa\/komiyakasa.jp\/public_html\/wp-content\/uploads\/pb_backupbuddy",
            "\/home\/komiyakasa\/komiyakasa.jp\/public_html\/wp-content\/uploads\/snapshots",
            "\/home\/komiyakasa\/komiyakasa.jp\/public_html\/wp-content\/uploads\/sucuri",
            "\/home\/komiyakasa\/komiyakasa.jp\/public_html\/wp-content\/uploads\/wp-clone",
            "\/home\/komiyakasa\/komiyakasa.jp\/public_html\/wp-content\/uploads\/wp_all_backup",
            "\/home\/komiyakasa\/komiyakasa.jp\/public_html\/wp-content\/uploads\/wpbackitup_backups",
            "\/home\/komiyakasa\/komiyakasa.jp\/public_html\/wp-content\/wfcache",
            "\/home\/komiyakasa\/komiyakasa.jp\/public_html\/wp-content\/wishlist-backup",
            "\/home\/komiyakasa\/komiyakasa.jp\/public_html\/wp-snapshots"
        ],
        "FilterFilesAll": [
            "error_log",
            "error.log",
            "debug_log",
            "ws_ftp.log",
            "dbcache",
            "pgcache",
            "objectcache",
            ".DS_Store",
            "\/home\/komiyakasa\/komiyakasa.jp\/public_html\/.htaccess",
            "\/home\/komiyakasa\/komiyakasa.jp\/public_html\/web.config",
            "\/home\/komiyakasa\/komiyakasa.jp\/public_html\/wp-config.php"
        ],
        "FilterExtsAll": [],
        "FilterInfo": {
            "Dirs": {
                "Warning": [],
                "Unreadable": [],
                "Core": [
                    "\/home\/komiyakasa\/komiyakasa.jp\/public_html\/wp-snapshots",
                    "\/home\/komiyakasa\/komiyakasa.jp\/public_html\/wp-content\/backups-dup-lite",
                    "\/home\/komiyakasa\/komiyakasa.jp\/public_html\/.opcache",
                    "\/home\/komiyakasa\/komiyakasa.jp\/public_html\/wp-content\/backups-dup-pro",
                    "\/home\/komiyakasa\/komiyakasa.jp\/public_html\/wp-content\/ai1wm-backups",
                    "\/home\/komiyakasa\/komiyakasa.jp\/public_html\/wp-content\/backupwordpress",
                    "\/home\/komiyakasa\/komiyakasa.jp\/public_html\/wp-content\/content\/cache",
                    "\/home\/komiyakasa\/komiyakasa.jp\/public_html\/wp-content\/contents\/cache",
                    "\/home\/komiyakasa\/komiyakasa.jp\/public_html\/wp-content\/infinitewp\/backups",
                    "\/home\/komiyakasa\/komiyakasa.jp\/public_html\/wp-content\/managewp\/backups",
                    "\/home\/komiyakasa\/komiyakasa.jp\/public_html\/wp-content\/old-cache",
                    "\/home\/komiyakasa\/komiyakasa.jp\/public_html\/wp-content\/plugins\/all-in-one-wp-migration\/storage",
                    "\/home\/komiyakasa\/komiyakasa.jp\/public_html\/wp-content\/updraft",
                    "\/home\/komiyakasa\/komiyakasa.jp\/public_html\/wp-content\/wishlist-backup",
                    "\/home\/komiyakasa\/komiyakasa.jp\/public_html\/wp-content\/wfcache",
                    "\/home\/komiyakasa\/komiyakasa.jp\/public_html\/wp-content\/bps-backup",
                    "\/home\/komiyakasa\/komiyakasa.jp\/public_html\/wp-content\/cache",
                    "\/home\/komiyakasa\/komiyakasa.jp\/public_html\/wp-content\/uploads\/aiowps_backups",
                    "\/home\/komiyakasa\/komiyakasa.jp\/public_html\/wp-content\/uploads\/backupbuddy_temp",
                    "\/home\/komiyakasa\/komiyakasa.jp\/public_html\/wp-content\/uploads\/backupbuddy_backups",
                    "\/home\/komiyakasa\/komiyakasa.jp\/public_html\/wp-content\/uploads\/ithemes-security\/backups",
                    "\/home\/komiyakasa\/komiyakasa.jp\/public_html\/wp-content\/uploads\/mainwp\/backup",
                    "\/home\/komiyakasa\/komiyakasa.jp\/public_html\/wp-content\/uploads\/pb_backupbuddy",
                    "\/home\/komiyakasa\/komiyakasa.jp\/public_html\/wp-content\/uploads\/snapshots",
                    "\/home\/komiyakasa\/komiyakasa.jp\/public_html\/wp-content\/uploads\/sucuri",
                    "\/home\/komiyakasa\/komiyakasa.jp\/public_html\/wp-content\/uploads\/wp-clone",
                    "\/home\/komiyakasa\/komiyakasa.jp\/public_html\/wp-content\/uploads\/wp_all_backup",
                    "\/home\/komiyakasa\/komiyakasa.jp\/public_html\/wp-content\/uploads\/wpbackitup_backups"
                ],
                "Global": [],
                "Instance": []
            },
            "Files": {
                "Size": [],
                "Warning": [],
                "Unreadable": [],
                "Core": [],
                "Global": [
                    "error_log",
                    "error.log",
                    "debug_log",
                    "ws_ftp.log",
                    "dbcache",
                    "pgcache",
                    "objectcache",
                    ".DS_Store"
                ],
                "Instance": []
            },
            "Exts": {
                "Core": [],
                "Global": [],
                "Instance": []
            },
            "UDirCount": 0,
            "UFileCount": 0,
            "UExtCount": 0,
            "TreeSize": [],
            "TreeWarning": []
        },
        "RecursiveLinks": [],
        "UnreadableItems": [],
        "Status": {
            "Size": "Good",
            "Names": "Good",
            "UnreadableItems": "Good",
            "MigratePackage": "Good",
            "CanbeMigratePackage": true,
            "showCreateProcStatus": "Good",
            "showCreateProc": true,
            "AddonSites": "Good"
        },
        "Dirs": [],
        "Files": []
    },
    "DB": {
        "Status": {
            "Success": true,
            "DB_Case": "Good",
            "DB_Rows": "Good",
            "DB_Size": "Good",
            "TBL_Case": "Good",
            "TBL_Rows": "Good",
            "TBL_Size": "Good"
        },
        "Size": "13.53MB",
        "Rows": "12,708",
        "TableCount": 22,
        "TableList": {
            "wp_actionscheduler_actions": {
                "Case": 0,
                "Rows": "15",
                "Size": "128KB",
                "USize": 131072
            },
            "wp_actionscheduler_claims": {
                "Case": 0,
                "Rows": "0",
                "Size": "32KB",
                "USize": 32768
            },
            "wp_actionscheduler_groups": {
                "Case": 0,
                "Rows": "2",
                "Size": "32KB",
                "USize": 32768
            },
            "wp_actionscheduler_logs": {
                "Case": 0,
                "Rows": "45",
                "Size": "48KB",
                "USize": 49152
            },
            "wp_commentmeta": {
                "Case": 0,
                "Rows": "0",
                "Size": "48KB",
                "USize": 49152
            },
            "wp_comments": {
                "Case": 0,
                "Rows": "0",
                "Size": "96KB",
                "USize": 98304
            },
            "wp_duplicator_packages": {
                "Case": 0,
                "Rows": "1",
                "Size": "32KB",
                "USize": 32768
            },
            "wp_links": {
                "Case": 0,
                "Rows": "0",
                "Size": "32KB",
                "USize": 32768
            },
            "wp_options": {
                "Case": 0,
                "Rows": "380",
                "Size": "2.13MB",
                "USize": 2228224
            },
            "wp_postmeta": {
                "Case": 0,
                "Rows": "7,179",
                "Size": "3.11MB",
                "USize": 3260416
            },
            "wp_posts": {
                "Case": 0,
                "Rows": "2,870",
                "Size": "7.17MB",
                "USize": 7520256
            },
            "wp_sbi_instagram_feeds_posts": {
                "Case": 0,
                "Rows": "25",
                "Size": "32KB",
                "USize": 32768
            },
            "wp_sbi_instagram_posts": {
                "Case": 0,
                "Rows": "25",
                "Size": "96KB",
                "USize": 98304
            },
            "wp_search_filter_cache": {
                "Case": 0,
                "Rows": "48",
                "Size": "64KB",
                "USize": 65536
            },
            "wp_search_filter_term_results": {
                "Case": 0,
                "Rows": "32",
                "Size": "64KB",
                "USize": 65536
            },
            "wp_term_relationships": {
                "Case": 0,
                "Rows": "1,675",
                "Size": "176KB",
                "USize": 180224
            },
            "wp_term_taxonomy": {
                "Case": 0,
                "Rows": "152",
                "Size": "48KB",
                "USize": 49152
            },
            "wp_termmeta": {
                "Case": 0,
                "Rows": "9",
                "Size": "48KB",
                "USize": 49152
            },
            "wp_terms": {
                "Case": 0,
                "Rows": "152",
                "Size": "48KB",
                "USize": 49152
            },
            "wp_usermeta": {
                "Case": 0,
                "Rows": "96",
                "Size": "48KB",
                "USize": 49152
            },
            "wp_users": {
                "Case": 0,
                "Rows": "2",
                "Size": "64KB",
                "USize": 65536
            },
            "wp_wpmailsmtp_tasks_meta": {
                "Case": 0,
                "Rows": "0",
                "Size": "16KB",
                "USize": 16384
            }
        },
        "RawSize": 14188544
    },
    "LL": {
        "TotalSize": "13.53MB",
        "Status": {
            "TotalSize": "Good"
        }
    }
}